MANIFEST.in
README.md
setup.py
Phoenix/App_Execute_Admin.py
Phoenix/App_Execute_User.py
Phoenix/App_Runtime_Admin.py
Phoenix/App_Runtime_User.py
Phoenix/Elevatex32.exe
Phoenix/Elevatex64.exe
Phoenix/Java_Delete.py
Phoenix/Java_Execute.py
Phoenix/Java_Path.py
Phoenix/Java_Save.py
Phoenix/Python_Delete.py
Phoenix/Python_Execute.py
Phoenix/Python_Path.py
Phoenix/Python_Save.py
Phoenix/VE_Java_Execute.py
Phoenix/VE_Python_Execute.py
Phoenix/__init__.py
Phoenix/Server/Receive_Data_Client.py
Phoenix/Server/Receive_Data_Server.py
Phoenix/Server/Send_Data_Client.py
Phoenix/Server/Send_Data_Server.py
Phoenix/Server/__init__.py
Phoenix_python.egg-info/PKG-INFO
Phoenix_python.egg-info/SOURCES.txt
Phoenix_python.egg-info/dependency_links.txt
Phoenix_python.egg-info/top_level.txt