Metadata-Version: 2.1
Name: Phoenix-python
Version: 2020.7.3
Summary: This is a pip-installable package for executing java and python programs together.
Home-page: https://github.com/Sam-Arora
Author: Sam Arora
Author-email: phoenix.language.official@gmail.com
License: MIT
Keywords: Phoenix,Java,Python,Java-Python Integration,phoenix,java,python,java-python integration
Platform: UNKNOWN
Classifier: Development Status :: 3 - Alpha
Classifier: Environment :: Win32 (MS Windows)
Classifier: Intended Audience :: Developers
Classifier: License :: OSI Approved :: MIT License
Classifier: Operating System :: Microsoft
Classifier: Programming Language :: Python
Classifier: Programming Language :: Python :: 3
Classifier: Programming Language :: Python :: 3.4
Classifier: Programming Language :: Python :: 3.5
Classifier: Programming Language :: Python :: 3.6
Classifier: Programming Language :: Python :: 3.7
Classifier: Topic :: Software Development
Classifier: Topic :: Software Development :: Libraries :: Python Modules
Classifier: Topic :: Utilities
